source/__init__.py
source/main.py
source/update_checker.py
source/update_package.py
boostedautocomplete-0.1.7.dist-info/METADATA
boostedautocomplete-0.1.7.dist-info/WHEEL
boostedautocomplete-0.1.7.dist-info/entry_points.txt
boostedautocomplete-0.1.7.dist-info/top_level.txt
boostedautocomplete-0.1.7.dist-info/RECORD
